nmr_classifier/__init__.py
nmr_classifier/admm_nmr.py
nmr_classifier/fast_admm_nmr.py
nmr_classifier/fast_admm_nmr_classifier.py
nmr_classifier-0.2.3.dist-info/METADATA
nmr_classifier-0.2.3.dist-info/WHEEL
nmr_classifier-0.2.3.dist-info/top_level.txt
nmr_classifier-0.2.3.dist-info/RECORD
