Metadata-Version: 2.1
Name: nmr-classifier
Version: 0.2.3
Summary: UNKNOWN
Home-page: https://github.com/riverKangg/nmr_classifier.git
Author: Jisun Kang
Author-email: riverkangg@gmail.com
License: UNKNOWN
Platform: UNKNOWN
Classifier: Programming Language :: Python :: 3
Classifier: Programming Language :: Python :: 3.2
Classifier: Programming Language :: Python :: 3.3
Classifier: Programming Language :: Python :: 3.4
Classifier: Programming Language :: Python :: 3.5
Classifier: Programming Language :: Python :: 3.6
Classifier: Programming Language :: Python :: 3.7
Requires-Python: >=3
